MANIFEST.in
README.rst
requirements.txt
setup.py
src/salscraper/__init__.py
src/salscraper/__main__.py
src/salscraper/core.py
src/salscraper/export.py
src/salscraper/extraction.py
src/salscraper/interface.py
src/salscraper/project.py
src/salscraper/scraper.py
src/salscraper/settings.py
src/salscraper.egg-info/PKG-INFO
src/salscraper.egg-info/SOURCES.txt
src/salscraper.egg-info/dependency_links.txt
src/salscraper.egg-info/not-zip-safe
src/salscraper.egg-info/requires.txt
src/salscraper.egg-info/top_level.txt